{
    "__comment": "Model generated using MrCrayfish's Model Creator (http://mrcrayfish.com/modelcreator/)",
    "parent": "block/cube_all",
    "elements": [
        {
            "name": "torso",
            "from": [ 6.800000011920929, 0.0, 2.0 ], 
            "to": [ 9.200000017881393, 16.0, 14.0 ], 
            "faces": {
                "north": { "texture": "#0", "uv": [ 0.0, 0.0, 2.0, 16.0 ] },
                "south": { "texture": "#0", "uv": [ 0.0, 0.0, 2.0, 16.0 ] }
            }
        },
        {
            "name": "torso",
            "from": [ 2.0, 0.0, 6.799999997019768 ], 
            "to": [ 14.0, 16.0, 9.200000002980232 ], 
            "faces": {
                "east": { "texture": "#0", "uv": [ 8.0, 0.0, 10.0, 16.0 ] },
                "west": { "texture": "#0", "uv": [ 8.0, 0.0, 10.0, 16.0 ] }
            }
        },
        {
            "name": "torso",
            "from": [ 6.800000011920929, 0.0, 2.0 ], 
            "to": [ 9.200000017881393, 16.0, 14.0 ], 
            "rotation": { "origin": [ 8.0, 8.0, 8.0 ], "axis": "y", "angle": 45.0 },
            "faces": {
                "north": { "texture": "#0", "uv": [ 4.0, 0.0, 6.0, 16.0 ] },
                "south": { "texture": "#0", "uv": [ 4.0, 0.0, 6.0, 16.0 ] }
            }
        },
        {
            "name": "torso",
            "from": [ 6.800000011920929, 0.0, 2.0 ], 
            "to": [ 9.200000017881393, 16.0, 14.0 ], 
            "rotation": { "origin": [ 8.0, 8.0, 8.0 ], "axis": "y", "angle": -45.0 },
            "faces": {
                "north": { "texture": "#0", "uv": [ 12.0, 0.0, 14.0, 16.0 ] },
                "south": { "texture": "#0", "uv": [ 12.0, 0.0, 14.0, 16.0 ] }
            }
        },
        {
            "name": "Cube",
            "from": [ 6.800000011920929, 0.0, 2.0 ], 
            "to": [ 9.200000017881393, 16.0, 14.0 ], 
            "rotation": { "origin": [ 8.0, 8.0, 8.0 ], "axis": "y", "angle": 22.5 },
            "faces": {
                "north": { "texture": "#0", "uv": [ 2.0, 0.0, 4.0, 16.0 ] },
                "south": { "texture": "#0", "uv": [ 2.0, 0.0, 4.0, 16.0 ] }
            }
        },
        {
            "name": "Cube",
            "from": [ 6.800000011920929, 0.0, 2.0 ], 
            "to": [ 9.200000017881393, 16.0, 14.0 ], 
            "rotation": { "origin": [ 8.0, 8.0, 8.0 ], "axis": "y", "angle": -22.5 },
            "faces": {
                "north": { "texture": "#0", "uv": [ 14.0, 0.0, 16.0, 16.0 ] },
                "south": { "texture": "#0", "uv": [ 14.0, 0.0, 16.0, 16.0 ] }
            }
        },
        {
            "name": "Cube",
            "from": [ 2.0, 0.0, 6.799999997019768 ], 
            "to": [ 14.0, 16.0, 9.200000002980232 ], 
            "rotation": { "origin": [ 8.0, 8.0, 8.0 ], "axis": "y", "angle": 22.5 },
            "faces": {
                "east": { "texture": "#0", "uv": [ 10.0, 0.0, 12.0, 16.0 ] },
                "west": { "texture": "#0", "uv": [ 10.0, 0.0, 12.0, 16.0 ] }
            }
        },
        {
            "name": "Cube",
            "from": [ 2.0, 0.0, 6.799999997019768 ], 
            "to": [ 14.0, 16.0, 9.200000002980232 ], 
            "rotation": { "origin": [ 8.0, 8.0, 8.0 ], "axis": "y", "angle": -22.5 },
            "faces": {
                "east": { "texture": "#0", "uv": [ 6.0, 0.0, 8.0, 16.0 ] },
                "west": { "texture": "#0", "uv": [ 6.0, 0.0, 8.0, 16.0 ] }
            }
        }
    ]
}